README.md
setup.cfg
setup.py
autodp/__init__.py
autodp/autodp_core.py
autodp/calibrator_zoo.py
autodp/converter.py
autodp/dp_acct.py
autodp/dp_bank.py
autodp/fdp_bank.py
autodp/mechanism_zoo.py
autodp/privacy_calibrator.py
autodp/rdp_acct.py
autodp/rdp_bank.py
autodp/transformer_zoo.py
autodp/utils.py
autodp.egg-info/PKG-INFO
autodp.egg-info/SOURCES.txt
autodp.egg-info/dependency_links.txt
autodp.egg-info/requires.txt
autodp.egg-info/top_level.txt