Metadata-Version: 1.1
Name: autodp
Version: 0.2
Summary: Automating Differential Privacy Computation
Home-page: https://github.com/yuxiangw/autodp
Author: Yu-Xiang Wang
Author-email: yuxiangw@cs.ucsb.edu
License: Apache
Download-URL: https://github.com/yuxiangw/autodp/archive/v0.2.tar.gz
Keywords: Differential Privacy,Moments Accountant,Renyi Differential Privacy
Platform: UNKNOWN
Classifier: Development Status :: 3 - Alpha
Classifier: Intended Audience :: Developers
Classifier: Intended Audience :: Science/Research
Classifier: Topic :: Scientific/Engineering :: Artificial Intelligence
Classifier: Topic :: Security
Classifier: License :: OSI Approved :: Apache Software License
Classifier: Programming Language :: Python :: 3
